Workbook

Sheet Start Here
A1: How to use this budget template
A3: 1) Go to Settings: set Plan Start Date and Selected Month (used by the Dashboard and payoff dates).
A4: 2) Go to Debts: enter each debt’s balance, APR, and monthly payments. 'Months to Payoff' and 'Payoff Date' calculate automatically.
A5: 3) Go to Goals: enter savings goals (target, current saved, monthly contribution).
A6: 4) Go to Budget: enter monthly amounts for Income, Savings, and Expenses. (Debt Payments pulls automatically from the Debts tab.)
A7: 5) Go to Dashboard: review charts + key insights (savings rate, debt-to-income, debt-free date, next goal date, runway, and more).
A9: Customization tips:
A10: • Expenses include 5 'Other' lines in most categories plus 10 'Custom' lines—rename any line item text to whatever you want.
A11: • If you don’t use a line item, leave it blank or 0 (zeros display as '-').
A13: Notes:
A14: • Debt payoff metrics assume constant monthly payments. If you change payments over time, update them as you go.
A15: • All calculations are done with regular Excel formulas (no dynamic array functions).
A16: • In Settings, set Emergency Fund Target (months) to see a target amount and gap on the Dashboard.

Sheet Settings
A1: Settings (Dashboard controls)
A3: Plan Start Date | B3: 45992
A4: Selected Month | B4: DEC
A5: Emergency Fund (Current) | B5: 0
A6: Cash/Savings Available (Current) | B6: 0
A7: Emergency Fund Target (months) | B7: 6
A8: Notes | B8: Update Plan Start Date and Selected Month to refresh the Dashboard and payoff dates.

Sheet Budget
A1: Personal Monthly Budget (Inputs)
A2: Year: | B2: 2025 | D2: Tip: Enter amounts in the month columns. Annual totals update automatically.
A3: Amounts are monthly. Leave unused cells blank or zero.
A4: Category | B4: Line Item | C4: JAN | D4: FEB | E4: MAR | F4: APR | G4: MAY | H4: JUN | I4: JUL | J4: AUG | K4: SEP | L4: OCT | M4: NOV | N4: DEC | O4: ANNUAL
A5: INCOME
A6: Income | B6: Paycheck 1 | C6: 0 | D6: 0 | E6: 0 | F6: 0 | G6: 0 | H6: 0 | I6: 0 | J6: 0 | K6: 0 | L6: 0 | M6: 0 | N6: 0 | O6: =SUM(C6:N6)
A7: Income | B7: Paycheck 2 | C7: 0 | D7: 0 | E7: 0 | F7: 0 | G7: 0 | H7: 0 | I7: 0 | J7: 0 | K7: 0 | L7: 0 | M7: 0 | N7: 0 | O7: =SUM(C7:N7)
A8: Income | B8: Side Income | C8: 0 | D8: 0 | E8: 0 | F8: 0 | G8: 0 | H8: 0 | I8: 0 | J8: 0 | K8: 0 | L8: 0 | M8: 0 | N8: 0 | O8: =SUM(C8:N8)
A9: Income | B9: Interest / Dividends | C9: 0 | D9: 0 | E9: 0 | F9: 0 | G9: 0 | H9: 0 | I9: 0 | J9: 0 | K9: 0 | L9: 0 | M9: 0 | N9: 0 | O9: =SUM(C9:N9)
A10: Income | B10: Other Income | C10: 0 | D10: 0 | E10: 0 | F10: 0 | G10: 0 | H10: 0 | I10: 0 | J10: 0 | K10: 0 | L10: 0 | M10: 0 | N10: 0 | O10: =SUM(C10:N10)
A11: Income | B11: Other #1 | C11: 0 | D11: 0 | E11: 0 | F11: 0 | G11: 0 | H11: 0 | I11: 0 | J11: 0 | K11: 0 | L11: 0 | M11: 0 | N11: 0 | O11: =SUM(C11:N11)
A12: Income | B12: Other #2 | C12: 0 | D12: 0 | E12: 0 | F12: 0 | G12: 0 | H12: 0 | I12: 0 | J12: 0 | K12: 0 | L12: 0 | M12: 0 | N12: 0 | O12: =SUM(C12:N12)
A13: Income | B13: Other #3 | C13: 0 | D13: 0 | E13: 0 | F13: 0 | G13: 0 | H13: 0 | I13: 0 | J13: 0 | K13: 0 | L13: 0 | M13: 0 | N13: 0 | O13: =SUM(C13:N13)
A14: Income | B14: Other #4 | C14: 0 | D14: 0 | E14: 0 | F14: 0 | G14: 0 | H14: 0 | I14: 0 | J14: 0 | K14: 0 | L14: 0 | M14: 0 | N14: 0 | O14: =SUM(C14:N14)
A15: Income | B15: Other #5 | C15: 0 | D15: 0 | E15: 0 | F15: 0 | G15: 0 | H15: 0 | I15: 0 | J15: 0 | K15: 0 | L15: 0 | M15: 0 | N15: 0 | O15: =SUM(C15:N15)
A16: Income | B16: Other #6 | C16: 0 | D16: 0 | E16: 0 | F16: 0 | G16: 0 | H16: 0 | I16: 0 | J16: 0 | K16: 0 | L16: 0 | M16: 0 | N16: 0 | O16: =SUM(C16:N16)
A17: Income | B17: Other #7 | C17: 0 | D17: 0 | E17: 0 | F17: 0 | G17: 0 | H17: 0 | I17: 0 | J17: 0 | K17: 0 | L17: 0 | M17: 0 | N17: 0 | O17: =SUM(C17:N17)
... A20: Income | B20: Other #10 | C20: 0 | D20: 0 | E20: 0 | F20: 0 | G20: 0 | H20: 0 | I20: 0 | J20: 0 | K20: 0 | L20: 0 | M20: 0 | N20: 0 | O20: =SUM(C20:N20)
A21: Income - Monthly Total | C21: =SUM(C6:C20) | D21: =SUM(D6:D20) | E21: =SUM(E6:E20) | F21: =SUM(F6:F20) | G21: =SUM(G6:G20) | H21: =SUM(H6:H20) | I21: =SUM(I6:I20) | J21: =SUM(J6:J20) | ... O21: =SUM(O6:O20)
A23: SAVINGS (Cash, Investments, Sinking Funds)
A24: Savings | B24: Savings and Investments | C24: 0 | D24: 0 | E24: 0 | F24: 0 | G24: 0 | H24: 0 | I24: 0 | J24: 0 | K24: 0 | L24: 0 | M24: 0 | N24: 0 | O24: =SUM(C24:N24)
A25: Savings | B25: Emergency Fund | C25: 0 | D25: 0 | E25: 0 | F25: 0 | G25: 0 | H25: 0 | I25: 0 | J25: 0 | K25: 0 | L25: 0 | M25: 0 | N25: 0 | O25: =SUM(C25:N25)
A26: Savings | B26: Retirement Savings | C26: 0 | D26: 0 | E26: 0 | F26: 0 | G26: 0 | H26: 0 | I26: 0 | J26: 0 | K26: 0 | L26: 0 | M26: 0 | N26: 0 | O26: =SUM(C26:N26)
A27: Savings | B27: College Savings | C27: 0 | D27: 0 | E27: 0 | F27: 0 | G27: 0 | H27: 0 | I27: 0 | J27: 0 | K27: 0 | L27: 0 | M27: 0 | N27: 0 | O27: =SUM(C27:N27)
A28: Savings | B28: Vacation Savings | C28: 0 | D28: 0 | E28: 0 | F28: 0 | G28: 0 | H28: 0 | I28: 0 | J28: 0 | K28: 0 | L28: 0 | M28: 0 | N28: 0 | O28: =SUM(C28:N28)
A29: Savings | B29: Other #1 | C29: 0 | D29: 0 | E29: 0 | F29: 0 | G29: 0 | H29: 0 | I29: 0 | J29: 0 | K29: 0 | L29: 0 | M29: 0 | N29: 0 | O29: =SUM(C29:N29)
A30: Savings | B30: Other #2 | C30: 0 | D30: 0 | E30: 0 | F30: 0 | G30: 0 | H30: 0 | I30: 0 | J30: 0 | K30: 0 | L30: 0 | M30: 0 | N30: 0 | O30: =SUM(C30:N30)
A31: Savings | B31: Other #3 | C31: 0 | D31: 0 | E31: 0 | F31: 0 | G31: 0 | H31: 0 | I31: 0 | J31: 0 | K31: 0 | L31: 0 | M31: 0 | N31: 0 | O31: =SUM(C31:N31)
A32: Savings | B32: Other #4 | C32: 0 | D32: 0 | E32: 0 | F32: 0 | G32: 0 | H32: 0 | I32: 0 | J32: 0 | K32: 0 | L32: 0 | M32: 0 | N32: 0 | O32: =SUM(C32:N32)
A33: Savings | B33: Other #5 | C33: 0 | D33: 0 | E33: 0 | F33: 0 | G33: 0 | H33: 0 | I33: 0 | J33: 0 | K33: 0 | L33: 0 | M33: 0 | N33: 0 | O33: =SUM(C33:N33)
A34: Savings | B34: Other #6 | C34: 0 | D34: 0 | E34: 0 | F34: 0 | G34: 0 | H34: 0 | I34: 0 | J34: 0 | K34: 0 | L34: 0 | M34: 0 | N34: 0 | O34: =SUM(C34:N34)
A35: Savings | B35: Other #7 | C35: 0 | D35: 0 | E35: 0 | F35: 0 | G35: 0 | H35: 0 | I35: 0 | J35: 0 | K35: 0 | L35: 0 | M35: 0 | N35: 0 | O35: =SUM(C35:N35)
... A38: Savings | B38: Other #10 | C38: 0 | D38: 0 | E38: 0 | F38: 0 | G38: 0 | H38: 0 | I38: 0 | J38: 0 | K38: 0 | L38: 0 | M38: 0 | N38: 0 | O38: =SUM(C38:N38)
A39: Savings - Monthly Total | C39: =SUM(C24:C38) | D39: =SUM(D24:D38) | E39: =SUM(E24:E38) | F39: =SUM(F24:F38) | G39: =SUM(G24:G38) | H39: =SUM(H24:H38) | I39: =SUM(I24:I38) | J39: =SUM(J24:J38) | ... O39: =SUM(O24:O38)
A41: EXPENSES
A42: HOME
A43: Home | B43: Mortgage / Rent | C43: 0 | D43: 0 | E43: 0 | F43: 0 | G43: 0 | H43: 0 | I43: 0 | J43: 0 | K43: 0 | L43: 0 | M43: 0 | N43: 0 | O43: =SUM(C43:N43)
A44: Home | B44: Home Insurance | C44: 0 | D44: 0 | E44: 0 | F44: 0 | G44: 0 | H44: 0 | I44: 0 | J44: 0 | K44: 0 | L44: 0 | M44: 0 | N44: 0 | O44: =SUM(C44:N44)
A45: Home | B45: Property Taxes | C45: 0 | D45: 0 | E45: 0 | F45: 0 | G45: 0 | H45: 0 | I45: 0 | J45: 0 | K45: 0 | L45: 0 | M45: 0 | N45: 0 | O45: =SUM(C45:N45)
A46: Home | B46: Home Maintenance & Repairs | C46: 0 | D46: 0 | E46: 0 | F46: 0 | G46: 0 | H46: 0 | I46: 0 | J46: 0 | K46: 0 | L46: 0 | M46: 0 | N46: 0 | O46: =SUM(C46:N46)
A47: Home | B47: Utilities (electric/gas/water) | C47: 0 | D47: 0 | E47: 0 | F47: 0 | G47: 0 | H47: 0 | I47: 0 | J47: 0 | K47: 0 | L47: 0 | M47: 0 | N47: 0 | O47: =SUM(C47:N47)
A48: Home | B48: Internet & Streaming | C48: 0 | D48: 0 | E48: 0 | F48: 0 | G48: 0 | H48: 0 | I48: 0 | J48: 0 | K48: 0 | L48: 0 | M48: 0 | N48: 0 | O48: =SUM(C48:N48)
A49: Home | B49: Other #1 | C49: 0 | D49: 0 | E49: 0 | F49: 0 | G49: 0 | H49: 0 | I49: 0 | J49: 0 | K49: 0 | L49: 0 | M49: 0 | N49: 0 | O49: =SUM(C49:N49)
A50: Home | B50: Other #2 | C50: 0 | D50: 0 | E50: 0 | F50: 0 | G50: 0 | H50: 0 | I50: 0 | J50: 0 | K50: 0 | L50: 0 | M50: 0 | N50: 0 | O50: =SUM(C50:N50)
A51: Home | B51: Other #3 | C51: 0 | D51: 0 | E51: 0 | F51: 0 | G51: 0 | H51: 0 | I51: 0 | J51: 0 | K51: 0 | L51: 0 | M51: 0 | N51: 0 | O51: =SUM(C51:N51)
A52: Home | B52: Other #4 | C52: 0 | D52: 0 | E52: 0 | F52: 0 | G52: 0 | H52: 0 | I52: 0 | J52: 0 | K52: 0 | L52: 0 | M52: 0 | N52: 0 | O52: =SUM(C52:N52)
A53: Home | B53: Other #5 | C53: 0 | D53: 0 | E53: 0 | F53: 0 | G53: 0 | H53: 0 | I53: 0 | J53: 0 | K53: 0 | L53: 0 | M53: 0 | N53: 0 | O53: =SUM(C53:N53)
A54: Home - Monthly Total | C54: =SUM(C43:C53) | D54: =SUM(D43:D53) | E54: =SUM(E43:E53) | F54: =SUM(F43:F53) | G54: =SUM(G43:G53) | H54: =SUM(H43:H53) | I54: =SUM(I43:I53) | J54: =SUM(J43:J53) | ... O54: =SUM(O43:O53)
A56: TRANSPORTATION
A57: Transportation | B57: Car Payment(s) | C57: 0 | D57: 0 | E57: 0 | F57: 0 | G57: 0 | H57: 0 | I57: 0 | J57: 0 | K57: 0 | L57: 0 | M57: 0 | N57: 0 | O57: =SUM(C57:N57)
A58: Transportation | B58: Fuel / Gasoline | C58: 0 | D58: 0 | E58: 0 | F58: 0 | G58: 0 | H58: 0 | I58: 0 | J58: 0 | K58: 0 | L58: 0 | M58: 0 | N58: 0 | O58: =SUM(C58:N58)
A59: Transportation | B59: Auto Insurance | C59: 0 | D59: 0 | E59: 0 | F59: 0 | G59: 0 | H59: 0 | I59: 0 | J59: 0 | K59: 0 | L59: 0 | M59: 0 | N59: 0 | O59: =SUM(C59:N59)
A60: Transportation | B60: Public Transportation / Rideshare | C60: 0 | D60: 0 | E60: 0 | F60: 0 | G60: 0 | H60: 0 | I60: 0 | J60: 0 | K60: 0 | L60: 0 | M60: 0 | N60: 0 | O60: =SUM(C60:N60)
A61: Transportation | B61: Auto Maintenance & Repairs | C61: 0 | D61: 0 | E61: 0 | F61: 0 | G61: 0 | H61: 0 | I61: 0 | J61: 0 | K61: 0 | L61: 0 | M61: 0 | N61: 0 | O61: =SUM(C61:N61)
A62: Transportation | B62: Other #1 | C62: 0 | D62: 0 | E62: 0 | F62: 0 | G62: 0 | H62: 0 | I62: 0 | J62: 0 | K62: 0 | L62: 0 | M62: 0 | N62: 0 | O62: =SUM(C62:N62)
A63: Transportation | B63: Other #2 | C63: 0 | D63: 0 | E63: 0 | F63: 0 | G63: 0 | H63: 0 | I63: 0 | J63: 0 | K63: 0 | L63: 0 | M63: 0 | N63: 0 | O63: =SUM(C63:N63)
A64: Transportation | B64: Other #3 | C64: 0 | D64: 0 | E64: 0 | F64: 0 | G64: 0 | H64: 0 | I64: 0 | J64: 0 | K64: 0 | L64: 0 | M64: 0 | N64: 0 | O64: =SUM(C64:N64)
A65: Transportation | B65: Other #4 | C65: 0 | D65: 0 | E65: 0 | F65: 0 | G65: 0 | H65: 0 | I65: 0 | J65: 0 | K65: 0 | L65: 0 | M65: 0 | N65: 0 | O65: =SUM(C65:N65)
A66: Transportation | B66: Other #5 | C66: 0 | D66: 0 | E66: 0 | F66: 0 | G66: 0 | H66: 0 | I66: 0 | J66: 0 | K66: 0 | L66: 0 | M66: 0 | N66: 0 | O66: =SUM(C66:N66)
A67: Transportation - Monthly Total | C67: =SUM(C57:C66) | D67: =SUM(D57:D66) | E67: =SUM(E57:E66) | F67: =SUM(F57:F66) | G67: =SUM(G57:G66) | H67: =SUM(H57:H66) | I67: =SUM(I57:I66) | J67: =SUM(J57:J66) | ... O67: =SUM(O57:O66)
A69: HEALTH
A70: Health | B70: Health Insurance | C70: 0 | D70: 0 | E70: 0 | F70: 0 | G70: 0 | H70: 0 | I70: 0 | J70: 0 | K70: 0 | L70: 0 | M70: 0 | N70: 0 | O70: =SUM(C70:N70)
A71: Health | B71: Medical (out-of-pocket) | C71: 0 | D71: 0 | E71: 0 | F71: 0 | G71: 0 | H71: 0 | I71: 0 | J71: 0 | K71: 0 | L71: 0 | M71: 0 | N71: 0 | O71: =SUM(C71:N71)
A72: Health | B72: Dental / Vision | C72: 0 | D72: 0 | E72: 0 | F72: 0 | G72: 0 | H72: 0 | I72: 0 | J72: 0 | K72: 0 | L72: 0 | M72: 0 | N72: 0 | O72: =SUM(C72:N72)
A73: Health | B73: Prescriptions | C73: 0 | D73: 0 | E73: 0 | F73: 0 | G73: 0 | H73: 0 | I73: 0 | J73: 0 | K73: 0 | L73: 0 | M73: 0 | N73: 0 | O73: =SUM(C73:N73)
A74: Health | B74: Other #1 | C74: 0 | D74: 0 | E74: 0 | F74: 0 | G74: 0 | H74: 0 | I74: 0 | J74: 0 | K74: 0 | L74: 0 | M74: 0 | N74: 0 | O74: =SUM(C74:N74)
A75: Health | B75: Other #2 | C75: 0 | D75: 0 | E75: 0 | F75: 0 | G75: 0 | H75: 0 | I75: 0 | J75: 0 | K75: 0 | L75: 0 | M75: 0 | N75: 0 | O75: =SUM(C75:N75)
A76: Health | B76: Other #3 | C76: 0 | D76: 0 | E76: 0 | F76: 0 | G76: 0 | H76: 0 | I76: 0 | J76: 0 | K76: 0 | L76: 0 | M76: 0 | N76: 0 | O76: =SUM(C76:N76)
A77: Health | B77: Other #4 | C77: 0 | D77: 0 | E77: 0 | F77: 0 | G77: 0 | H77: 0 | I77: 0 | J77: 0 | K77: 0 | L77: 0 | M77: 0 | N77: 0 | O77: =SUM(C77:N77)
A78: Health | B78: Other #5 | C78: 0 | D78: 0 | E78: 0 | F78: 0 | G78: 0 | H78: 0 | I78: 0 | J78: 0 | K78: 0 | L78: 0 | M78: 0 | N78: 0 | O78: =SUM(C78:N78)
A79: Health - Monthly Total | C79: =SUM(C70:C78) | D79: =SUM(D70:D78) | E79: =SUM(E70:E78) | F79: =SUM(F70:F78) | G79: =SUM(G70:G78) | H79: =SUM(H70:H78) | I79: =SUM(I70:I78) | J79: =SUM(J70:J78) | ... O79: =SUM(O70:O78)
A81: DAILY LIVING
A82: Daily Living | B82: Groceries | C82: 0 | D82: 0 | E82: 0 | F82: 0 | G82: 0 | H82: 0 | I82: 0 | J82: 0 | K82: 0 | L82: 0 | M82: 0 | N82: 0 | O82: =SUM(C82:N82)
A83: Daily Living | B83: Household Supplies | C83: 0 | D83: 0 | E83: 0 | F83: 0 | G83: 0 | H83: 0 | I83: 0 | J83: 0 | K83: 0 | L83: 0 | M83: 0 | N83: 0 | O83: =SUM(C83:N83)
A84: Daily Living | B84: Clothing & Shoes | C84: 0 | D84: 0 | E84: 0 | F84: 0 | G84: 0 | H84: 0 | I84: 0 | J84: 0 | K84: 0 | L84: 0 | M84: 0 | N84: 0 | O84: =SUM(C84:N84)
A85: Daily Living | B85: Childcare / School Fees | C85: 0 | D85: 0 | E85: 0 | F85: 0 | G85: 0 | H85: 0 | I85: 0 | J85: 0 | K85: 0 | L85: 0 | M85: 0 | N85: 0 | O85: =SUM(C85:N85)
A86: Daily Living | B86: Pet Care | C86: 0 | D86: 0 | E86: 0 | F86: 0 | G86: 0 | H86: 0 | I86: 0 | J86: 0 | K86: 0 | L86: 0 | M86: 0 | N86: 0 | O86: =SUM(C86:N86)
A87: Daily Living | B87: Other #1 | C87: 0 | D87: 0 | E87: 0 | F87: 0 | G87: 0 | H87: 0 | I87: 0 | J87: 0 | K87: 0 | L87: 0 | M87: 0 | N87: 0 | O87: =SUM(C87:N87)
A88: Daily Living | B88: Other #2 | C88: 0 | D88: 0 | E88: 0 | F88: 0 | G88: 0 | H88: 0 | I88: 0 | J88: 0 | K88: 0 | L88: 0 | M88: 0 | N88: 0 | O88: =SUM(C88:N88)
A89: Daily Living | B89: Other #3 | C89: 0 | D89: 0 | E89: 0 | F89: 0 | G89: 0 | H89: 0 | I89: 0 | J89: 0 | K89: 0 | L89: 0 | M89: 0 | N89: 0 | O89: =SUM(C89:N89)
A90: Daily Living | B90: Other #4 | C90: 0 | D90: 0 | E90: 0 | F90: 0 | G90: 0 | H90: 0 | I90: 0 | J90: 0 | K90: 0 | L90: 0 | M90: 0 | N90: 0 | O90: =SUM(C90:N90)
A91: Daily Living | B91: Other #5 | C91: 0 | D91: 0 | E91: 0 | F91: 0 | G91: 0 | H91: 0 | I91: 0 | J91: 0 | K91: 0 | L91: 0 | M91: 0 | N91: 0 | O91: =SUM(C91:N91)
A92: Daily Living - Monthly Total | C92: =SUM(C82:C91) | D92: =SUM(D82:D91) | E92: =SUM(E82:E91) | F92: =SUM(F82:F91) | G92: =SUM(G82:G91) | H92: =SUM(H82:H91) | I92: =SUM(I82:I91) | J92: =SUM(J82:J91) | ... O92: =SUM(O82:O91)
A94: ENTERTAINMENT
A95: Entertainment | B95: Dining Out | C95: 0 | D95: 0 | E95: 0 | F95: 0 | G95: 0 | H95: 0 | I95: 0 | J95: 0 | K95: 0 | L95: 0 | M95: 0 | N95: 0 | O95: =SUM(C95:N95)
A96: Entertainment | B96: Entertainment & Subscriptions | C96: 0 | D96: 0 | E96: 0 | F96: 0 | G96: 0 | H96: 0 | I96: 0 | J96: 0 | K96: 0 | L96: 0 | M96: 0 | N96: 0 | O96: =SUM(C96:N96)
A97: Entertainment | B97: Hobbies / Recreation | C97: 0 | D97: 0 | E97: 0 | F97: 0 | G97: 0 | H97: 0 | I97: 0 | J97: 0 | K97: 0 | L97: 0 | M97: 0 | N97: 0 | O97: =SUM(C97:N97)
A98: Entertainment | B98: Travel / Vacation | C98: 0 | D98: 0 | E98: 0 | F98: 0 | G98: 0 | H98: 0 | I98: 0 | J98: 0 | K98: 0 | L98: 0 | M98: 0 | N98: 0 | O98: =SUM(C98:N98)
A99: Entertainment | B99: Other #1 | C99: 0 | D99: 0 | E99: 0 | F99: 0 | G99: 0 | H99: 0 | I99: 0 | J99: 0 | K99: 0 | L99: 0 | M99: 0 | N99: 0 | O99: =SUM(C99:N99)
A100: Entertainment | B100: Other #2 | C100: 0 | D100: 0 | E100: 0 | F100: 0 | G100: 0 | H100: 0 | I100: 0 | J100: 0 | K100: 0 | L100: 0 | M100: 0 | N100: 0 | O100: =SUM(C100:N100)
A101: Entertainment | B101: Other #3 | C101: 0 | D101: 0 | E101: 0 | F101: 0 | G101: 0 | H101: 0 | I101: 0 | J101: 0 | K101: 0 | L101: 0 | M101: 0 | N101: 0 | O101: =SUM(C101:N101)
A102: Entertainment | B102: Other #4 | C102: 0 | D102: 0 | E102: 0 | F102: 0 | G102: 0 | H102: 0 | I102: 0 | J102: 0 | K102: 0 | L102: 0 | M102: 0 | N102: 0 | O102: =SUM(C102:N102)
A103: Entertainment | B103: Other #5 | C103: 0 | D103: 0 | E103: 0 | F103: 0 | G103: 0 | H103: 0 | I103: 0 | J103: 0 | K103: 0 | L103: 0 | M103: 0 | N103: 0 | O103: =SUM(C103:N103)
A104: Entertainment - Monthly Total | C104: =SUM(C95:C103) | D104: =SUM(D95:D103) | E104: =SUM(E95:E103) | F104: =SUM(F95:F103) | G104: =SUM(G95:G103) | H104: =SUM(H95:H103) | I104: =SUM(I95:I103) | J104: =SUM(J95:J103) | ... O104: =SUM(O95:O103)
A106: PERSONAL & FAMILY
A107: Personal & Family | B107: Personal Care | C107: 0 | D107: 0 | E107: 0 | F107: 0 | G107: 0 | H107: 0 | I107: 0 | J107: 0 | K107: 0 | L107: 0 | M107: 0 | N107: 0 | O107: =SUM(C107:N107)
A108: Personal & Family | B108: Gifts & Celebrations | C108: 0 | D108: 0 | E108: 0 | F108: 0 | G108: 0 | H108: 0 | I108: 0 | J108: 0 | K108: 0 | L108: 0 | M108: 0 | N108: 0 | O108: =SUM(C108:N108)
A109: Personal & Family | B109: Education & Development | C109: 0 | D109: 0 | E109: 0 | F109: 0 | G109: 0 | H109: 0 | I109: 0 | J109: 0 | K109: 0 | L109: 0 | M109: 0 | N109: 0 | O109: =SUM(C109:N109)
A110: Personal & Family | B110: Memberships & Subscriptions | C110: 0 | D110: 0 | E110: 0 | F110: 0 | G110: 0 | H110: 0 | I110: 0 | J110: 0 | K110: 0 | L110: 0 | M110: 0 | N110: 0 | O110: =SUM(C110:N110)
A111: Personal & Family | B111: Other #1 | C111: 0 | D111: 0 | E111: 0 | F111: 0 | G111: 0 | H111: 0 | I111: 0 | J111: 0 | K111: 0 | L111: 0 | M111: 0 | N111: 0 | O111: =SUM(C111:N111)
...

Sheet Debts
A1: Debt Tracker (Payoff metrics)
A2: Enter each debt below. Payoff calculations assume constant monthly payment.
A4: Debt Name | B4: Type | C4: Current Balance | D4: APR | E4: Min Payment | F4: Extra Payment | G4: Total Payment | H4: Include in Budget? | I4: Months to Payoff | J4: Payoff Date | K4: Est. Interest Paid | L4: Notes
C5: 0 | D5: 0 | E5: 0 | F5: 0 | G5: =E5+F5 | H5: TRUE | I5: =IF(G5<=0,"",IF(D5=0,C5/G5,IF(G5<=C5*D5/12,"Payment too low",NPER(D5/12,-G5,C5)))) | J5: =IFERROR(EDATE(Settings!$B$3,ROUNDUP(I5,0)),"") | K5: =IF(OR(I5="",ISTEXT(I5)),"",G5*I5-C5)
C6: 0 | D6: 0 | E6: 0 | F6: 0 | G6: =E6+F6 | H6: TRUE | I6: =IF(G6<=0,"",IF(D6=0,C6/G6,IF(G6<=C6*D6/12,"Payment too low",NPER(D6/12,-G6,C6)))) | J6: =IFERROR(EDATE(Settings!$B$3,ROUNDUP(I6,0)),"") | K6: =IF(OR(I6="",ISTEXT(I6)),"",G6*I6-C6)
C7: 0 | D7: 0 | E7: 0 | F7: 0 | G7: =E7+F7 | H7: TRUE | I7: =IF(G7<=0,"",IF(D7=0,C7/G7,IF(G7<=C7*D7/12,"Payment too low",NPER(D7/12,-G7,C7)))) | J7: =IFERROR(EDATE(Settings!$B$3,ROUNDUP(I7,0)),"") | K7: =IF(OR(I7="",ISTEXT(I7)),"",G7*I7-C7)
C8: 0 | D8: 0 | E8: 0 | F8: 0 | G8: =E8+F8 | H8: TRUE | I8: =IF(G8<=0,"",IF(D8=0,C8/G8,IF(G8<=C8*D8/12,"Payment too low",NPER(D8/12,-G8,C8)))) | J8: =IFERROR(EDATE(Settings!$B$3,ROUNDUP(I8,0)),"") | K8: =IF(OR(I8="",ISTEXT(I8)),"",G8*I8-C8)
C9: 0 | D9: 0 | E9: 0 | F9: 0 | G9: =E9+F9 | H9: TRUE | I9: =IF(G9<=0,"",IF(D9=0,C9/G9,IF(G9<=C9*D9/12,"Payment too low",NPER(D9/12,-G9,C9)))) | J9: =IFERROR(EDATE(Settings!$B$3,ROUNDUP(I9,0)),"") | K9: =IF(OR(I9="",ISTEXT(I9)),"",G9*I9-C9)
C10: 0 | D10: 0 | E10: 0 | F10: 0 | G10: =E10+F10 | H10: TRUE | I10: =IF(G10<=0,"",IF(D10=0,C10/G10,IF(G10<=C10*D10/12,"Payment too low",NPER(D10/12,-G10,C10)))) | J10: =IFERROR(EDATE(Settings!$B$3,ROUNDUP(I10,0)),"") | K10: =IF(OR(I10="",ISTEXT(I10)),"",G10*I10-C10)
C11: 0 | D11: 0 | E11: 0 | F11: 0 | G11: =E11+F11 | H11: TRUE | I11: =IF(G11<=0,"",IF(D11=0,C11/G11,IF(G11<=C11*D11/12,"Payment too low",NPER(D11/12,-G11,C11)))) | J11: =IFERROR(EDATE(Settings!$B$3,ROUNDUP(I11,0)),"") | K11: =IF(OR(I11="",ISTEXT(I11)),"",G11*I11-C11)
C12: 0 | D12: 0 | E12: 0 | F12: 0 | G12: =E12+F12 | H12: TRUE | I12: =IF(G12<=0,"",IF(D12=0,C12/G12,IF(G12<=C12*D12/12,"Payment too low",NPER(D12/12,-G12,C12)))) | J12: =IFERROR(EDATE(Settings!$B$3,ROUNDUP(I12,0)),"") | K12: =IF(OR(I12="",ISTEXT(I12)),"",G12*I12-C12)
C13: 0 | D13: 0 | E13: 0 | F13: 0 | G13: =E13+F13 | H13: TRUE | I13: =IF(G13<=0,"",IF(D13=0,C13/G13,IF(G13<=C13*D13/12,"Payment too low",NPER(D13/12,-G13,C13)))) | J13: =IFERROR(EDATE(Settings!$B$3,ROUNDUP(I13,0)),"") | K13: =IF(OR(I13="",ISTEXT(I13)),"",G13*I13-C13)
C14: 0 | D14: 0 | E14: 0 | F14: 0 | G14: =E14+F14 | H14: TRUE | I14: =IF(G14<=0,"",IF(D14=0,C14/G14,IF(G14<=C14*D14/12,"Payment too low",NPER(D14/12,-G14,C14)))) | J14: =IFERROR(EDATE(Settings!$B$3,ROUNDUP(I14,0)),"") | K14: =IF(OR(I14="",ISTEXT(I14)),"",G14*I14-C14)
C15: 0 | D15: 0 | E15: 0 | F15: 0 | G15: =E15+F15 | H15: TRUE | I15: =IF(G15<=0,"",IF(D15=0,C15/G15,IF(G15<=C15*D15/12,"Payment too low",NPER(D15/12,-G15,C15)))) | J15: =IFERROR(EDATE(Settings!$B$3,ROUNDUP(I15,0)),"") | K15: =IF(OR(I15="",ISTEXT(I15)),"",G15*I15-C15)
C16: 0 | D16: 0 | E16: 0 | F16: 0 | G16: =E16+F16 | H16: TRUE | I16: =IF(G16<=0,"",IF(D16=0,C16/G16,IF(G16<=C16*D16/12,"Payment too low",NPER(D16/12,-G16,C16)))) | J16: =IFERROR(EDATE(Settings!$B$3,ROUNDUP(I16,0)),"") | K16: =IF(OR(I16="",ISTEXT(I16)),"",G16*I16-C16)
... C54: 0 | D54: 0 | E54: 0 | F54: 0 | G54: =E54+F54 | H54: TRUE | I54: =IF(G54<=0,"",IF(D54=0,C54/G54,IF(G54<=C54*D54/12,"Payment too low",NPER(D54/12,-G54,C54)))) | J54: =IFERROR(EDATE(Settings!$B$3,ROUNDUP(I54,0)),"") | K54: =IF(OR(I54="",ISTEXT(I54)),"",G54*I54-C54)
A57: Debt Summary
A58: Total Debt Balance | B58: =SUMIF(H5:H54,TRUE,C5:C54)
A59: Total Monthly Debt Payment | B59: =SUMIF(H5:H54,TRUE,G5:G54)
A60: Debt-Free Date (latest payoff) | B60: =IFERROR(AGGREGATE(14,6,J5:J54/(H5:H54=TRUE),1),"")
A61: Total Est. Interest (all debts) | B61: =SUMIF(H5:H54,TRUE,K5:K54)

Sheet Goals
A1: Savings Goals (time-to-goal metrics)
A2: Add goals below (e.g., Emergency Fund, Vacation, Down Payment). Dashboard will summarize your progress.
A4: Goal Name | B4: Type | C4: Target Amount | D4: Current Saved | E4: Monthly Contribution | F4: Remaining | G4: Months to Goal | H4: Goal Date | I4: Notes
C5: 0 | D5: 0 | E5: 0 | F5: =MAX(0,C5-D5) | G5: =IF(E5<=0,"",F5/E5) | H5: =IFERROR(EDATE(Settings!$B$3,ROUNDUP(G5,0)),"")
C6: 0 | D6: 0 | E6: 0 | F6: =MAX(0,C6-D6) | G6: =IF(E6<=0,"",F6/E6) | H6: =IFERROR(EDATE(Settings!$B$3,ROUNDUP(G6,0)),"")
C7: 0 | D7: 0 | E7: 0 | F7: =MAX(0,C7-D7) | G7: =IF(E7<=0,"",F7/E7) | H7: =IFERROR(EDATE(Settings!$B$3,ROUNDUP(G7,0)),"")
C8: 0 | D8: 0 | E8: 0 | F8: =MAX(0,C8-D8) | G8: =IF(E8<=0,"",F8/E8) | H8: =IFERROR(EDATE(Settings!$B$3,ROUNDUP(G8,0)),"")
C9: 0 | D9: 0 | E9: 0 | F9: =MAX(0,C9-D9) | G9: =IF(E9<=0,"",F9/E9) | H9: =IFERROR(EDATE(Settings!$B$3,ROUNDUP(G9,0)),"")
C10: 0 | D10: 0 | E10: 0 | F10: =MAX(0,C10-D10) | G10: =IF(E10<=0,"",F10/E10) | H10: =IFERROR(EDATE(Settings!$B$3,ROUNDUP(G10,0)),"")
C11: 0 | D11: 0 | E11: 0 | F11: =MAX(0,C11-D11) | G11: =IF(E11<=0,"",F11/E11) | H11: =IFERROR(EDATE(Settings!$B$3,ROUNDUP(G11,0)),"")
C12: 0 | D12: 0 | E12: 0 | F12: =MAX(0,C12-D12) | G12: =IF(E12<=0,"",F12/E12) | H12: =IFERROR(EDATE(Settings!$B$3,ROUNDUP(G12,0)),"")
C13: 0 | D13: 0 | E13: 0 | F13: =MAX(0,C13-D13) | G13: =IF(E13<=0,"",F13/E13) | H13: =IFERROR(EDATE(Settings!$B$3,ROUNDUP(G13,0)),"")
C14: 0 | D14: 0 | E14: 0 | F14: =MAX(0,C14-D14) | G14: =IF(E14<=0,"",F14/E14) | H14: =IFERROR(EDATE(Settings!$B$3,ROUNDUP(G14,0)),"")
C15: 0 | D15: 0 | E15: 0 | F15: =MAX(0,C15-D15) | G15: =IF(E15<=0,"",F15/E15) | H15: =IFERROR(EDATE(Settings!$B$3,ROUNDUP(G15,0)),"")
C16: 0 | D16: 0 | E16: 0 | F16: =MAX(0,C16-D16) | G16: =IF(E16<=0,"",F16/E16) | H16: =IFERROR(EDATE(Settings!$B$3,ROUNDUP(G16,0)),"")
... C44: 0 | D44: 0 | E44: 0 | F44: =MAX(0,C44-D44) | G44: =IF(E44<=0,"",F44/E44) | H44: =IFERROR(EDATE(Settings!$B$3,ROUNDUP(G44,0)),"")
A47: Goals Summary
A48: Total Target | B48: =SUM(C5:C44)
A49: Total Saved | B49: =SUM(D5:D44)
A50: Total Monthly Contributions | B50: =SUM(E5:E44)
A51: Next Goal Date (soonest) | B51: =IFERROR(AGGREGATE(15,6,H5:H44/(F5:F44>0)/(E5:E44>0),1),"")

Sheet Dashboard
A1: Dashboard (Charts & Insights)
A3: Plan Start Date | B3: =Settings!B3 | D3: Selected Month | E3: =Settings!B4 | G3: Year | H3: =Budget!B2 | J3: Month Index | K3: =MATCH(Settings!$B$4,Budget!$C$4:$N$4,0)
A4: Emergency Fund (Current) | B4: =Settings!B5 | D4: Cash/Savings Available | E4: =Settings!B6
A6: Income (Selected Month) | D6: Savings (Selected Month) | G6: Expenses (Selected Month) | J6: Net Cash Flow
A7: =INDEX(Budget!$C$21:$N$21,$K$3) | D7: =INDEX(Budget!$C$39:$N$39,$K$3) | G7: =INDEX(Budget!$C$154:$N$154,$K$3) | J7: =INDEX(Budget!$C$156:$N$156,$K$3)
A9: Savings Rate | B9: =IFERROR(D7/A7,0) | D9: Debt-to-Income | E9: =IFERROR(Debts!$B$59/A7,0) | G9: Emergency Fund Coverage (months) | H9: =IFERROR(B4/G7,0) | J9: Runway (months) | K9: =IFERROR(E4/G7,0)
A10: Fixed Expenses (Home+Trans+Health+Debt) | B10: =INDEX(Budget!$C$54:$N$54,$K$3)+INDEX(Budget!$C$67:$N$67,$K$3)+INDEX(Budget!$C$79:$N$79,$K$3)+INDEX(Budget!$C$130:$N$130,$K$3) | D10: Fixed % of Income | E10: =IFERROR(B10/A7,0) | G10: Variable Expenses | H10: =G7-B10 | J10: Break-even (Expenses+Savings) | K10: =G7+D7
A11: Debt-Free Date | B11: =Debts!$B$60 | D11: Total Debt Balance | E11: =Debts!$B$58 | G11: Total Monthly Debt Payment | H11: =Debts!$B$59 | J11: Next Goal Date | K11: =Goals!$B$51
A12: Total Est. Interest (All Debts) | B12: =Debts!$B$61 | D12: Monthly Contributions (All Goals) | E12: =Goals!$B$50 | J12: Potential Extra to Save/Pay Debt | K12: =MAX(0,J7)
A13: Emergency Fund Target Amount | B13: =Settings!$B$7*G7 | D13: Emergency Fund Gap | E13: =MAX(0,B13-B4)
A14: Expense Breakdown (Selected Month)
A15: Category | B15: Amount
A16: Home | B16: =INDEX(Budget!$C$54:$N$54,$K$3)
A17: Transportation | B17: =INDEX(Budget!$C$67:$N$67,$K$3)
A18: Health | B18: =INDEX(Budget!$C$79:$N$79,$K$3)
A19: Daily Living | B19: =INDEX(Budget!$C$92:$N$92,$K$3)
A20: Entertainment | B20: =INDEX(Budget!$C$104:$N$104,$K$3)
A21: Personal & Family | B21: =INDEX(Budget!$C$116:$N$116,$K$3)
A22: Giving | B22: =INDEX(Budget!$C$126:$N$126,$K$3)
A23: Debt Payments | B23: =INDEX(Budget!$C$130:$N$130,$K$3) | D23: Selected Month Snapshot
A24: Misc / Other | B24: =INDEX(Budget!$C$139:$N$139,$K$3) | D24: Metric | E24: Amount
A25: Custom Expenses (Rename items as needed) | B25: =INDEX(Budget!$C$152:$N$152,$K$3) | D25: Income | E25: =A7
D26: Savings | E26: =D7
D27: Expenses | E27: =G7
D28: Net Cash Flow | E28: =J7
